README.rst
setup.py
hikvision_recover/__init__.py
hikvision_recover/recover.py
hikvision_recover.egg-info/PKG-INFO
hikvision_recover.egg-info/SOURCES.txt
hikvision_recover.egg-info/dependency_links.txt
hikvision_recover.egg-info/entry_points.txt
hikvision_recover.egg-info/top_level.txt