Metadata-Version: 1.1
Name: hikvision-recover
Version: 1.0.1
Summary: Command-line tool for generating recovery codes for Hikvision IP Cameras
Home-page: https://github.com/spyoungtech/hikvision-recover/
Author: Spencer Young
Author-email: spencer.young@spyoung.com
License: MIT
Platform: any
Classifier: Operating System :: OS Independent
Classifier: Programming Language :: Python
